pipe_stat.py
test/__init__.py
test/test_all.py
pipe_stat-0.0.6.dist-info/LICENSE
pipe_stat-0.0.6.dist-info/METADATA
pipe_stat-0.0.6.dist-info/WHEEL
pipe_stat-0.0.6.dist-info/entry_points.txt
pipe_stat-0.0.6.dist-info/top_level.txt
pipe_stat-0.0.6.dist-info/RECORD
