Metadata-Version: 2.1
Name: pipe-stat
Version: 0.0.6
Summary: Get the status of your GitLab pipelines right into your terminal.
Home-page: https://github.com/M0r13n/pipe-stat
Author: Leon Morten Richter
Author-email: leon.morten@gmail.com
License: MIT
Keywords: Gitlab,Pipeline,Status,Monitor
Platform: UNKNOWN
Classifier: Programming Language :: Python :: 3
Classifier: License :: OSI Approved :: MIT License
Classifier: Operating System :: OS Independent
Classifier: Intended Audience :: Developers
Classifier: Typing :: Typed
Requires-Python: >=3.6
Requires-Dist: python-gitlab
Requires-Dist: tabulate
Requires-Dist: python-dateutil
